[
    {
        "date": "14-05-2026",
        "text": "**Perfect in Place** has been placed at **#32**, above **Epic Multiplayer** and below **i just wish i could**."
    },
    {
        "date": "14-04-2026",
        "text": "**Geochroma Reminisce** has been placed at **#11**, above **me when machine gang** and below **Horros**."
    },
    {
        "date": "30-03-2026",
        "text": "**in this together** has been lowered from **#50** to **#52**, above **123 Charisma** and below **See**."
    },
    {
        "date": "15-03-2026",
        "text": "**Neon Aurora** has been raised from **#71** to **#66**, above **Temple Profanators** and below **The MasterSonic**."
    }
]
